README.md
celery_error_emails.py
setup.py
celery_error_emails.egg-info/PKG-INFO
celery_error_emails.egg-info/SOURCES.txt
celery_error_emails.egg-info/dependency_links.txt
celery_error_emails.egg-info/top_level.txt