Metadata-Version: 1.1
Name: celery-error-emails
Version: 0.1
Summary: Automatically send error emails about failing Celery tasks in your Django project.
Home-page: https://github.com/mherrmann/celery_error_emails
Author: Michael Herrmann
Author-email: michaelREMOVETHISIFYOUAREHUMAN@herrmann.io
License: MIT
Keywords: celery error emails django
Platform: UNKNOWN
Classifier: Development Status :: 3 - Alpha
Classifier: Framework :: Django
Classifier: Framework :: Celery
Classifier: License :: OSI Approved :: MIT License
Classifier: Programming Language :: Python :: 3
